microdrop_device_converter/__init__.py
microdrop_device_converter/__main__.py
microdrop_device_converter/dmf_device.py
microdrop_device_converter-0.1.post5.dist-info/DESCRIPTION.rst
microdrop_device_converter-0.1.post5.dist-info/METADATA
microdrop_device_converter-0.1.post5.dist-info/RECORD
microdrop_device_converter-0.1.post5.dist-info/WHEEL
microdrop_device_converter-0.1.post5.dist-info/metadata.json
microdrop_device_converter-0.1.post5.dist-info/pbr.json
microdrop_device_converter-0.1.post5.dist-info/top_level.txt
