Metadata-Version: 2.0
Name: microdrop-device-converter
Version: 0.1.post5
Summary: Convert microdrop devices from v0.3.0 to SVG format.
Home-page: https://github.com/wheeler-microfluidics/microdrop-device-converter
Author: Christian Fobel
Author-email: christian@fobel.net
License: LGPLv2.1
Platform: UNKNOWN
Requires-Dist: microdrop-utility (>=0.4)
Requires-Dist: numpy
Requires-Dist: pandas
Requires-Dist: path-helpers (>=0.2)
Requires-Dist: pyyaml
Requires-Dist: svg-model (>=0.5.post14)
